{
    "pages": [
        // 首页
        {
            "path": "pages/index/index",
            "style": {
                "navigationBarTitleText": "基础组件"
            }
        },

        // 扩展组件
        {
            "path": "pages/extend/extend",
            "style": {
                "navigationBarTitleText": "扩展组件"
            }
        },

        // 图标
        {
            "path": "pages/icon/icon",
            "style": {
                "navigationBarTitleText": "图标"
            }
        },

        // 状态栏
        {
            "path": "pages/status-bar/status-bar",
            "style": {
                "navigationBarTitleText": "状态栏"
            }
        },

        // 导航栏
        {
            "path": "pages/navigation-bar/navigation-bar",
            "style": {
                "navigationBarTitleText": "导航栏"
            }
        },

        // 按钮
        {
            "path": "pages/button/button",
            "style": {
                "navigationBarTitleText": "按钮"
            }
        },

        // 轮播
        {
            "path": "pages/swiper/swiper",
            "style": {
                "navigationBarTitleText": "轮播"
            }
        },

        // 轮播指示器
        {
            "path": "pages/swiper-indicator/swiper-indicator",
            "style": {
                "navigationBarTitleText": "轮播指示器"
            }
        },

        // 滚动通知
        {
            "path": "pages/notice-bar/notice-bar",
            "style": {
                "navigationBarTitleText": "滚动通知"
            }
        },

        // 价格
        {
            "path": "pages/price/price",
            "style": {
                "navigationBarTitleText": "价格"
            }
        },

        // 图片
        {
            "path": "pages/image/image",
            "style": {
                "navigationBarTitleText": "图片"
            }
        },

        // loading - 加载
        {
            "path": "pages/loading/loading",
            "style": {
                "navigationBarTitleText": "loading - 加载"
            }
        },

        // 内容为空
        {
            "path": "pages/empty/empty",
            "style": {
                "navigationBarTitleText": "内容为空"
            }
        },

        // 加载更多
        {
            "path": "pages/loadmore/loadmore",
            "style": {
                "navigationBarTitleText": "加载更多"
            }
        },

        // 可拖动按钮
        {
            "path": "pages/movable-button/movable-button",
            "style": {
                "navigationBarTitleText": "可拖动按钮"
            }
        },

        // 电梯导航
        {
            "path": "pages/elevator/elevator",
            "style": {
                "navigationBarTitleText": "电梯导航"
            }
        },

        // 徽标数
        {
            "path": "pages/badge/badge",
            "style": {
                "navigationBarTitleText": "徽标数"
            }
        },

        // 过滤器
        {
            "path": "pages/filter/filter",
            "style": {
                "navigationBarTitleText": "过滤器"
            }
        },

        // 商品组件
        {
            "path": "pages/goods/goods",
            "style": {
                "navigationBarTitleText": "商品组件"
            }
        },

        // 分类组件
        {
            "path": "pages/classify/classify",
            "style": {
                "navigationBarTitleText": "分类组件"
            }
        },

        // 商品/物品属性组件
        {
            "path": "pages/attrs/attrs",
            "style": {
                "navigationBarTitleText": "商品/物品属性组件"
            }
        },

        // 商品/物品参数组件
        {
            "path": "pages/params/params",
            "style": {
                "navigationBarTitleText": "商品/物品参数组件"
            }
        },

        // 固定在页面底部的组件
        {
            "path": "pages/fixed-bottom/fixed-bottom",
            "style": {
                "navigationBarTitleText": "固定在页面底部的组件"
            }
        },

        // 步进器
        {
            "path": "pages/number-step/number-step",
            "style": {
                "navigationBarTitleText": "步进器"
            }
        },

        // 标签
        {
            "path": "pages/tag/tag",
            "style": {
                "navigationBarTitleText": "标签"
            }
        },

        // 复选框
        {
            "path": "pages/checkbox/checkbox",
            "style": {
                "navigationBarTitleText": "复选框"
            }
        },

        // 复选框组
        {
            "path": "pages/checkbox-group/checkbox-group",
            "style": {
                "navigationBarTitleText": "复选框组"
            }
        },

        // 遮罩层
        {
            "path": "pages/overlay/overlay",
            "style": {
                "navigationBarTitleText": "遮罩层"
            }
        },

        // 弹出层
        {
            "path": "pages/popup/popup",
            "style": {
                "navigationBarTitleText": "弹出层"
            }
        },

        // 倒计时
        {
            "path": "pages/countdown/countdown",
            "style": {
                "navigationBarTitleText": "倒计时"
            }
        },

        // 头像组
        {
            "path": "pages/avatar-group/avatar-group",
            "style": {
                "navigationBarTitleText": "头像组"
            }
        },

        // 单选框
        {
            "path": "pages/radio/radio",
            "style": {
                "navigationBarTitleText": "单选框"
            }
        },

        // 单选框组
        {
            "path": "pages/radio-group/radio-group",
            "style": {
                "navigationBarTitleText": "单选框组"
            }
        }
    ],
    "subPackages": [{
        "root": "subPackages/goods",
        "pages": [{
            "path": "pages/aster",
            "style": {
                "navigationBarTitleText": "商品-紫菀-aster"
            }
        }, {
            "path": "pages/bamboo",
            "style": {
                "navigationBarTitleText": "商品-竹-bamboo"
            }
        }]
    }, {
        "root": "subPackages/classify",
        "pages": [{
            "path": "pages/aster",
            "style": {
                "navigationBarTitleText": "分类-紫菀-aster"
            }
        }]
    }, {
        "root": "subPackages/attrs",
        "pages": [{
            "path": "pages/aster",
            "style": {
                "navigationBarTitleText": "商品/物品属性-紫菀-aster"
            }
        }]
    }, {
        "root": "subPackages/params",
        "pages": [{
            "path": "pages/aster",
            "style": {
                "navigationBarTitleText": "商品/物品参数-紫菀-aster"
            }
        }]
    }, {
        "root": "subPackages/fixed-bottom",
        "pages": [{
            "path": "pages/aster",
            "style": {
                "navigationBarTitleText": "底部组件-紫菀-aster"
            }
        }, {
            "path": "pages/bamboo",
            "style": {
                "navigationBarTitleText": "底部组件-竹-bamboo"
            }
        }, {
            "path": "pages/camellia",
            "style": {
                "navigationBarTitleText": "底部组件-山茶花-camellia"
            }
        }]
    }],
    "globalStyle": {
        "navigationBarTextStyle": "black",
        "navigationBarTitleText": "hi-ui",
        "navigationBarBackgroundColor": "#ffffff",
        "backgroundColor": "#ffffff"
    },
    "tabBar": {
        "backgroundColor": "#ffffff",
        "borderStyle": "black",
        "color": "#888888",
        "selectedColor": "#FF6068",
        "list": [{
                "iconPath": "static/tabBar/icons/index.png",
                "selectedIconPath": "static/tabBar/icons/index_selected.png",
                "text": "基础组件",
                "pagePath": "pages/index/index"
            },
            {
                "iconPath": "static/tabBar/icons/extend.png",
                "selectedIconPath": "static/tabBar/icons/extend_selected.png",
                "text": "扩展组件",
                "pagePath": "pages/extend/extend"
            }
        ]
    }
}